{"trial_id": "07", "hyperparameters": {"space": [{"class_name": "Int", "config": {"name": "units_1", "default": null, "conditions": [], "min_value": 16, "max_value": 256, "step": 16, "sampling": "linear"}}, {"class_name": "Float", "config": {"name": "dropout_1", "default": 0.1, "conditions": [], "min_value": 0.1, "max_value": 0.4, "step": 0.1, "sampling": "linear"}}, {"class_name": "Int", "config": {"name": "units_2", "default": null, "conditions": [], "min_value": 8, "max_value": 64, "step": 8, "sampling": "linear"}}, {"class_name": "Choice", "config": {"name": "learning_rate", "default": 1e-05, "conditions": [], "values": [1e-05, 0.0001, 0.001, 0.01], "ordered": true}}], "values": {"units_1": 192, "dropout_1": 0.4, "units_2": 40, "learning_rate": 0.0001}}, "metrics": {"metrics": {"loss": {"direction": "min", "observations": [{"value": [0.00670049712061882], "step": 4}]}, "root_mean_squared_error": {"direction": "min", "observations": [{"value": [0.08185656368732452], "step": 4}]}, "val_loss": {"direction": "min", "observations": [{"value": [0.007744987960904837], "step": 4}]}, "val_root_mean_squared_error": {"direction": "min", "observations": [{"value": [0.08800560981035233], "step": 4}]}}}, "score": 0.007744987960904837, "best_step": 4, "status": "COMPLETED", "message": null}